mvbc/__init__.py
mvbc/auth.py
mvbc/client.py
mvbc/config.py
mvbc/data_getter.py
mvbc/objects.py
mvbc/version.py
mvbc-0.1.0.dist-info/LICENSE
mvbc-0.1.0.dist-info/METADATA
mvbc-0.1.0.dist-info/WHEEL
mvbc-0.1.0.dist-info/RECORD
