Metadata-Version: 2.3
Name: mvbc
Version: 0.1.0
Summary: This is a Python package to directly interact with the Meetnet Vlaamse Banken api and get the publically available weather data in the Belgian North Sea directly.
Home-page: https://github.com/WEILMAX/mvbc
Author: Maximillian Weil
Author-email: maximillian.f.weil@gmail.com
Requires-Python: >=3.9,<4.0
Classifier: Programming Language :: Python :: 3
Classifier: Programming Language :: Python :: 3.9
Classifier: Programming Language :: Python :: 3.10
Classifier: Programming Language :: Python :: 3.11
Classifier: Programming Language :: Python :: 3.12
Classifier: Programming Language :: Python :: 3.13
Requires-Dist: geopy (>=2.4.1,<3.0.0)
Requires-Dist: numpy (>=1.19.4)
Requires-Dist: pandas (>=1.15)
Requires-Dist: pydantic (<2.0)
Requires-Dist: requests (>=2.32.3,<3.0.0)
Project-URL: Documentation, https://WEILMAX.github.io/mvbc/
Project-URL: Repository, https://github.com/WEILMAX/mvbc
